[
    {
      "id": "b487796c7ba8ac2cbacf371fc2c3d67b",
      "sport_key": "baseball_mlb",
      "sport_title": "MLB",
      "commence_time": "2023-04-29T16:10:00Z",
      "home_team": "Detroit Tigers",
      "away_team": "Baltimore Orioles",
      "bookmakers": [
        {
          "key": "fanduel",
          "title": "FanDuel",
          "last_update": "2023-04-29T13:59:41Z",
          "markets": [
            {
              "key": "spreads",
              "last_update": "2023-04-29T13:59:41Z",
              "outcomes": [
                {
                  "name": "Baltimore Orioles",
                  "price": 142,
                  "point": -1.5
                },
                {
                  "name": "Detroit Tigers",
                  "price": -172,
                  "point": 1.5
                }
              ]
            },
            {
              "key": "totals",
              "last_update": "2023-04-29T13:59:41Z",
              "outcomes": [
                {
                  "name": "Over",
                  "price": -110,
                  "point": 8
                },
                {
                  "name": "Under",
                  "price": -110,
                  "point": 8
                }
              ]
            }
          ]
        }
      ]
    },
    {
      "id": "587d0692ea7bb2395bfd962ef6dcef52",
      "sport_key": "baseball_mlb",
      "sport_title": "MLB",
      "commence_time": "2023-04-29T17:05:00Z",
      "home_team": "Washington Nationals",
      "away_team": "Pittsburgh Pirates",
      "bookmakers": [
        {
          "key": "fanduel",
          "title": "FanDuel",
          "last_update": "2023-04-29T13:59:41Z",
          "markets": [
            {
              "key": "spreads",
              "last_update": "2023-04-29T13:59:41Z",
              "outcomes": [
                {
                  "name": "Pittsburgh Pirates",
                  "price": 116,
                  "point": -1.5
                },
                {
                  "name": "Washington Nationals",
                  "price": -142,
                  "point": 1.5
                }
              ]
            },
            {
              "key": "totals",
              "last_update": "2023-04-29T13:59:41Z",
              "outcomes": [
                {
                  "name": "Over",
                  "price": -118,
                  "point": 9
                },
                {
                  "name": "Under",
                  "price": -104,
                  "point": 9
                }
              ]
            }
          ]
        }
      ]
    },
    {
      "id": "eec30b92e328d39161d8c37fc346132d",
      "sport_key": "baseball_mlb",
      "sport_title": "MLB",
      "commence_time": "2023-04-29T18:10:00Z",
      "home_team": "Minnesota Twins",
      "away_team": "Kansas City Royals",
      "bookmakers": [
        {
          "key": "fanduel",
          "title": "FanDuel",
          "last_update": "2023-04-29T13:59:41Z",
          "markets": [
            {
              "key": "spreads",
              "last_update": "2023-04-29T13:59:41Z",
              "outcomes": [
                {
                  "name": "Kansas City Royals",
                  "price": -106,
                  "point": 1.5
                },
                {
                  "name": "Minnesota Twins",
                  "price": -113,
                  "point": -1.5
                }
              ]
            },
            {
              "key": "totals",
              "last_update": "2023-04-29T13:59:41Z",
              "outcomes": [
                {
                  "name": "Over",
                  "price": -114,
                  "point": 8
                },
                {
                  "name": "Under",
                  "price": -106,
                  "point": 8
                }
              ]
            }
          ]
        }
      ]
    },
    {
      "id": "bc228957c48565c87f965dd41e7db26a",
      "sport_key": "baseball_mlb",
      "sport_title": "MLB",
      "commence_time": "2023-04-29T19:07:00Z",
      "home_team": "Toronto Blue Jays",
      "away_team": "Seattle Mariners",
      "bookmakers": [
        {
          "key": "fanduel",
          "title": "FanDuel",
          "last_update": "2023-04-29T13:59:41Z",
          "markets": [
            {
              "key": "spreads",
              "last_update": "2023-04-29T13:59:41Z",
              "outcomes": [
                {
                  "name": "Seattle Mariners",
                  "price": 110,
                  "point": 1.5
                },
                {
                  "name": "Toronto Blue Jays",
                  "price": -132,
                  "point": -1.5
                }
              ]
            },
            {
              "key": "totals",
              "last_update": "2023-04-29T13:59:41Z",
              "outcomes": [
                {
                  "name": "Over",
                  "price": -112,
                  "point": 9
                },
                {
                  "name": "Under",
                  "price": -108,
                  "point": 9
                }
              ]
            }
          ]
        }
      ]
    },
    {
      "id": "f50b77d82dff01f6f43dd82c30677edc",
      "sport_key": "baseball_mlb",
      "sport_title": "MLB",
      "commence_time": "2023-04-29T20:05:00Z",
      "home_team": "New York Mets",
      "away_team": "Atlanta Braves",
      "bookmakers": [
        {
          "key": "fanduel",
          "title": "FanDuel",
          "last_update": "2023-04-29T13:59:41Z",
          "markets": [
            {
              "key": "spreads",
              "last_update": "2023-04-29T13:59:41Z",
              "outcomes": [
                {
                  "name": "Atlanta Braves",
                  "price": 104,
                  "point": -1.5
                },
                {
                  "name": "New York Mets",
                  "price": -125,
                  "point": 1.5
                }
              ]
            },
            {
              "key": "totals",
              "last_update": "2023-04-29T13:59:41Z",
              "outcomes": [
                {
                  "name": "Over",
                  "price": -110,
                  "point": 7.5
                },
                {
                  "name": "Under",
                  "price": -110,
                  "point": 7.5
                }
              ]
            }
          ]
        }
      ]
    },
    {
      "id": "15c1b4122e3bc462d8010def52f5d804",
      "sport_key": "baseball_mlb",
      "sport_title": "MLB",
      "commence_time": "2023-04-29T20:05:00Z",
      "home_team": "Miami Marlins",
      "away_team": "Chicago Cubs",
      "bookmakers": [
        {
          "key": "fanduel",
          "title": "FanDuel",
          "last_update": "2023-04-29T13:59:41Z",
          "markets": [
            {
              "key": "spreads",
              "last_update": "2023-04-29T13:59:41Z",
              "outcomes": [
                {
                  "name": "Chicago Cubs",
                  "price": -192,
                  "point": 1.5
                },
                {
                  "name": "Miami Marlins",
                  "price": 158,
                  "point": -1.5
                }
              ]
            },
            {
              "key": "totals",
              "last_update": "2023-04-29T13:59:41Z",
              "outcomes": [
                {
                  "name": "Over",
                  "price": 100,
                  "point": 9
                },
                {
                  "name": "Under",
                  "price": -122,
                  "point": 9
                }
              ]
            }
          ]
        }
      ]
    },
    {
      "id": "aa0a2446323fafd7643d481fe44c7beb",
      "sport_key": "baseball_mlb",
      "sport_title": "MLB",
      "commence_time": "2023-04-29T20:07:00Z",
      "home_team": "Oakland Athletics",
      "away_team": "Cincinnati Reds",
      "bookmakers": [
        {
          "key": "fanduel",
          "title": "FanDuel",
          "last_update": "2023-04-29T13:59:41Z",
          "markets": [
            {
              "key": "spreads",
              "last_update": "2023-04-29T13:59:41Z",
              "outcomes": [
                {
                  "name": "Cincinnati Reds",
                  "price": 106,
                  "point": -1.5
                },
                {
                  "name": "Oakland Athletics",
                  "price": -128,
                  "point": 1.5
                }
              ]
            },
            {
              "key": "totals",
              "last_update": "2023-04-29T13:59:41Z",
              "outcomes": [
                {
                  "name": "Over",
                  "price": -114,
                  "point": 7.5
                },
                {
                  "name": "Under",
                  "price": -106,
                  "point": 7.5
                }
              ]
            }
          ]
        }
      ]
    },
    {
      "id": "55b086d6b65f8ca053907a487e4933c2",
      "sport_key": "baseball_mlb",
      "sport_title": "MLB",
      "commence_time": "2023-04-29T20:10:00Z",
      "home_team": "Boston Red Sox",
      "away_team": "Cleveland Guardians",
      "bookmakers": [
        {
          "key": "fanduel",
          "title": "FanDuel",
          "last_update": "2023-04-29T13:59:41Z",
          "markets": [
            {
              "key": "spreads",
              "last_update": "2023-04-29T13:59:41Z",
              "outcomes": [
                {
                  "name": "Boston Red Sox",
                  "price": 150,
                  "point": -1.5
                },
                {
                  "name": "Cleveland Guardians",
                  "price": -182,
                  "point": 1.5
                }
              ]
            },
            {
              "key": "totals",
              "last_update": "2023-04-29T13:59:41Z",
              "outcomes": [
                {
                  "name": "Over",
                  "price": 100,
                  "point": 9
                },
                {
                  "name": "Under",
                  "price": -122,
                  "point": 9
                }
              ]
            }
          ]
        }
      ]
    },
    {
      "id": "f5c12e09695bb49deacaee1d38268575",
      "sport_key": "baseball_mlb",
      "sport_title": "MLB",
      "commence_time": "2023-04-29T21:10:00Z",
      "home_team": "Detroit Tigers",
      "away_team": "Baltimore Orioles",
      "bookmakers": [
        {
          "key": "fanduel",
          "title": "FanDuel",
          "last_update": "2023-04-29T13:59:41Z",
          "markets": [
            {
              "key": "spreads",
              "last_update": "2023-04-29T13:59:41Z",
              "outcomes": [
                {
                  "name": "Baltimore Orioles",
                  "price": 104,
                  "point": -1.5
                },
                {
                  "name": "Detroit Tigers",
                  "price": -125,
                  "point": 1.5
                }
              ]
            },
            {
              "key": "totals",
              "last_update": "2023-04-29T13:59:41Z",
              "outcomes": [
                {
                  "name": "Over",
                  "price": -115,
                  "point": 7.5
                },
                {
                  "name": "Under",
                  "price": -105,
                  "point": 7.5
                }
              ]
            }
          ]
        }
      ]
    },
    {
      "id": "7c9e8528c8ada9a6cebcb82c9f87a576",
      "sport_key": "baseball_mlb",
      "sport_title": "MLB",
      "commence_time": "2023-04-29T21:10:00Z",
      "home_team": "Houston Astros",
      "away_team": "Philadelphia Phillies",
      "bookmakers": [
        {
          "key": "fanduel",
          "title": "FanDuel",
          "last_update": "2023-04-29T13:59:41Z",
          "markets": [
            {
              "key": "spreads",
              "last_update": "2023-04-29T13:59:41Z",
              "outcomes": [
                {
                  "name": "Houston Astros",
                  "price": 158,
                  "point": -1.5
                },
                {
                  "name": "Philadelphia Phillies",
                  "price": -192,
                  "point": 1.5
                }
              ]
            },
            {
              "key": "totals",
              "last_update": "2023-04-29T13:59:41Z",
              "outcomes": [
                {
                  "name": "Over",
                  "price": -106,
                  "point": 7.5
                },
                {
                  "name": "Under",
                  "price": -114,
                  "point": 7.5
                }
              ]
            }
          ]
        }
      ]
    },
    {
      "id": "9728590934fbd6e7372026019fef8b6b",
      "sport_key": "baseball_mlb",
      "sport_title": "MLB",
      "commence_time": "2023-04-29T22:05:00Z",
      "home_team": "Washington Nationals",
      "away_team": "Pittsburgh Pirates",
      "bookmakers": [
        {
          "key": "fanduel",
          "title": "FanDuel",
          "last_update": "2023-04-29T13:59:41Z",
          "markets": [
            {
              "key": "spreads",
              "last_update": "2023-04-29T13:59:41Z",
              "outcomes": [
                {
                  "name": "Pittsburgh Pirates",
                  "price": 116,
                  "point": -1.5
                },
                {
                  "name": "Washington Nationals",
                  "price": -140,
                  "point": 1.5
                }
              ]
            },
            {
              "key": "totals",
              "last_update": "2023-04-29T13:59:41Z",
              "outcomes": [
                {
                  "name": "Over",
                  "price": -108,
                  "point": 9
                },
                {
                  "name": "Under",
                  "price": -112,
                  "point": 9
                }
              ]
            }
          ]
        }
      ]
    },
    {
      "id": "b66da318e22b5a330fc384b407e40c30",
      "sport_key": "baseball_mlb",
      "sport_title": "MLB",
      "commence_time": "2023-04-29T22:05:00Z",
      "home_team": "San Diego Padres",
      "away_team": "San Francisco Giants",
      "bookmakers": [
        {
          "key": "fanduel",
          "title": "FanDuel",
          "last_update": "2023-04-29T13:59:41Z",
          "markets": [
            {
              "key": "spreads",
              "last_update": "2023-04-29T13:59:41Z",
              "outcomes": [
                {
                  "name": "San Diego Padres",
                  "price": -111,
                  "point": -1.5
                },
                {
                  "name": "San Francisco Giants",
                  "price": -108,
                  "point": 1.5
                }
              ]
            },
            {
              "key": "totals",
              "last_update": "2023-04-29T13:59:41Z",
              "outcomes": [
                {
                  "name": "Over",
                  "price": -108,
                  "point": 15.5
                },
                {
                  "name": "Under",
                  "price": -112,
                  "point": 15.5
                }
              ]
            }
          ]
        }
      ]
    },
    {
      "id": "abc6b7f30e64849a3442c7b8642bcbcf",
      "sport_key": "baseball_mlb",
      "sport_title": "MLB",
      "commence_time": "2023-04-29T23:05:00Z",
      "home_team": "Texas Rangers",
      "away_team": "New York Yankees",
      "bookmakers": [
        {
          "key": "fanduel",
          "title": "FanDuel",
          "last_update": "2023-04-29T13:59:41Z",
          "markets": [
            {
              "key": "spreads",
              "last_update": "2023-04-29T13:59:41Z",
              "outcomes": [
                {
                  "name": "New York Yankees",
                  "price": -162,
                  "point": 1.5
                },
                {
                  "name": "Texas Rangers",
                  "price": 134,
                  "point": -1.5
                }
              ]
            },
            {
              "key": "totals",
              "last_update": "2023-04-29T13:59:41Z",
              "outcomes": [
                {
                  "name": "Over",
                  "price": -110,
                  "point": 8.5
                },
                {
                  "name": "Under",
                  "price": -110,
                  "point": 8.5
                }
              ]
            }
          ]
        }
      ]
    },
    {
      "id": "47e5e45cb6af47aac35520869d28dbc0",
      "sport_key": "baseball_mlb",
      "sport_title": "MLB",
      "commence_time": "2023-04-29T23:10:00Z",
      "home_team": "Chicago White Sox",
      "away_team": "Tampa Bay Rays",
      "bookmakers": [
        {
          "key": "fanduel",
          "title": "FanDuel",
          "last_update": "2023-04-29T13:59:41Z",
          "markets": [
            {
              "key": "spreads",
              "last_update": "2023-04-29T13:59:41Z",
              "outcomes": [
                {
                  "name": "Chicago White Sox",
                  "price": -156,
                  "point": 1.5
                },
                {
                  "name": "Tampa Bay Rays",
                  "price": 130,
                  "point": -1.5
                }
              ]
            },
            {
              "key": "totals",
              "last_update": "2023-04-29T13:59:41Z",
              "outcomes": [
                {
                  "name": "Over",
                  "price": -120,
                  "point": 9
                },
                {
                  "name": "Under",
                  "price": -102,
                  "point": 9
                }
              ]
            }
          ]
        }
      ]
    },
    {
      "id": "a7997fde5de5da18cbfc430846202cc8",
      "sport_key": "baseball_mlb",
      "sport_title": "MLB",
      "commence_time": "2023-04-29T23:10:00Z",
      "home_team": "Milwaukee Brewers",
      "away_team": "Los Angeles Angels",
      "bookmakers": [
        {
          "key": "fanduel",
          "title": "FanDuel",
          "last_update": "2023-04-29T13:59:41Z",
          "markets": [
            {
              "key": "spreads",
              "last_update": "2023-04-29T13:59:41Z",
              "outcomes": [
                {
                  "name": "Los Angeles Angels",
                  "price": -154,
                  "point": 1.5
                },
                {
                  "name": "Milwaukee Brewers",
                  "price": 128,
                  "point": -1.5
                }
              ]
            },
            {
              "key": "totals",
              "last_update": "2023-04-29T13:59:41Z",
              "outcomes": [
                {
                  "name": "Over",
                  "price": -114,
                  "point": 8
                },
                {
                  "name": "Under",
                  "price": -106,
                  "point": 8
                }
              ]
            }
          ]
        }
      ]
    },
    {
      "id": "8f39471186ed6e6797271f17b46ef217",
      "sport_key": "baseball_mlb",
      "sport_title": "MLB",
      "commence_time": "2023-04-30T00:10:00Z",
      "home_team": "Colorado Rockies",
      "away_team": "Arizona Diamondbacks",
      "bookmakers": [
        {
          "key": "fanduel",
          "title": "FanDuel",
          "last_update": "2023-04-29T13:59:41Z",
          "markets": [
            {
              "key": "spreads",
              "last_update": "2023-04-29T13:59:41Z",
              "outcomes": [
                {
                  "name": "Arizona Diamondbacks",
                  "price": 130,
                  "point": -1.5
                },
                {
                  "name": "Colorado Rockies",
                  "price": -160,
                  "point": 1.5
                }
              ]
            },
            {
              "key": "totals",
              "last_update": "2023-04-29T13:59:41Z",
              "outcomes": [
                {
                  "name": "Over",
                  "price": -114,
                  "point": 12.5
                },
                {
                  "name": "Under",
                  "price": -106,
                  "point": 12.5
                }
              ]
            }
          ]
        }
      ]
    },
    {
      "id": "ca92087430f9656446b21a61917de2bb",
      "sport_key": "baseball_mlb",
      "sport_title": "MLB",
      "commence_time": "2023-04-30T01:10:00Z",
      "home_team": "Los Angeles Dodgers",
      "away_team": "St. Louis Cardinals",
      "bookmakers": [
        {
          "key": "fanduel",
          "title": "FanDuel",
          "last_update": "2023-04-29T13:59:41Z",
          "markets": [
            {
              "key": "spreads",
              "last_update": "2023-04-29T13:59:41Z",
              "outcomes": [
                {
                  "name": "Los Angeles Dodgers",
                  "price": 140,
                  "point": -1.5
                },
                {
                  "name": "St. Louis Cardinals",
                  "price": -170,
                  "point": 1.5
                }
              ]
            },
            {
              "key": "totals",
              "last_update": "2023-04-29T13:59:41Z",
              "outcomes": [
                {
                  "name": "Over",
                  "price": -112,
                  "point": 8
                },
                {
                  "name": "Under",
                  "price": -108,
                  "point": 8
                }
              ]
            }
          ]
        }
      ]
    },
    {
      "id": "c949d3c4f30433076bafdf69c1e51d5d",
      "sport_key": "baseball_mlb",
      "sport_title": "MLB",
      "commence_time": "2023-04-30T16:05:00Z",
      "home_team": "Miami Marlins",
      "away_team": "Chicago Cubs",
      "bookmakers": [
        
      ]
    },
    {
      "id": "c5ce1e9821853b48a63c1bca9f8de439",
      "sport_key": "baseball_mlb",
      "sport_title": "MLB",
      "commence_time": "2023-04-30T17:35:00Z",
      "home_team": "Boston Red Sox",
      "away_team": "Cleveland Guardians",
      "bookmakers": [
        
      ]
    },
    {
      "id": "cd1ba3db9d916b7b6dc634dd49a5f6fb",
      "sport_key": "baseball_mlb",
      "sport_title": "MLB",
      "commence_time": "2023-04-30T17:37:00Z",
      "home_team": "Toronto Blue Jays",
      "away_team": "Seattle Mariners",
      "bookmakers": [
        
      ]
    },
    {
      "id": "791d3b3866fb1cb887550deea0fa70df",
      "sport_key": "baseball_mlb",
      "sport_title": "MLB",
      "commence_time": "2023-04-30T18:10:00Z",
      "home_team": "Chicago White Sox",
      "away_team": "Tampa Bay Rays",
      "bookmakers": [
        
      ]
    },
    {
      "id": "f1198ef3d05c9eebc1bc97d88d6f359a",
      "sport_key": "baseball_mlb",
      "sport_title": "MLB",
      "commence_time": "2023-04-30T18:10:00Z",
      "home_team": "Minnesota Twins",
      "away_team": "Kansas City Royals",
      "bookmakers": [
        
      ]
    },
    {
      "id": "6d03aceaa9d0a57cbd196ff854e19924",
      "sport_key": "baseball_mlb",
      "sport_title": "MLB",
      "commence_time": "2023-04-30T18:10:00Z",
      "home_team": "Milwaukee Brewers",
      "away_team": "Los Angeles Angels",
      "bookmakers": [
        
      ]
    },
    {
      "id": "e3b33f68d5eef4c2feb8939046c5c5c3",
      "sport_key": "baseball_mlb",
      "sport_title": "MLB",
      "commence_time": "2023-04-30T18:35:00Z",
      "home_team": "Texas Rangers",
      "away_team": "New York Yankees",
      "bookmakers": [
        
      ]
    },
    {
      "id": "c56ebf255ed5b3905fb4c2cd32fb1eca",
      "sport_key": "baseball_mlb",
      "sport_title": "MLB",
      "commence_time": "2023-04-30T19:10:00Z",
      "home_team": "Colorado Rockies",
      "away_team": "Arizona Diamondbacks",
      "bookmakers": [
        
      ]
    },
    {
      "id": "793fd4271c4b703b7384c05e399f62f7",
      "sport_key": "baseball_mlb",
      "sport_title": "MLB",
      "commence_time": "2023-04-30T20:07:00Z",
      "home_team": "Oakland Athletics",
      "away_team": "Cincinnati Reds",
      "bookmakers": [
        
      ]
    },
    {
      "id": "75214037c234afa2564a0cf70be6856b",
      "sport_key": "baseball_mlb",
      "sport_title": "MLB",
      "commence_time": "2023-04-30T20:10:00Z",
      "home_team": "Los Angeles Dodgers",
      "away_team": "St. Louis Cardinals",
      "bookmakers": [
        
      ]
    },
    {
      "id": "d8c3479002d2c2cc382b18fcad4eeff9",
      "sport_key": "baseball_mlb",
      "sport_title": "MLB",
      "commence_time": "2023-04-30T23:10:00Z",
      "home_team": "Houston Astros",
      "away_team": "Philadelphia Phillies",
      "bookmakers": [
        
      ]
    }
  ]